nagra_panorama_api/__init__.py
nagra_panorama_api/__main__.py
nagra_panorama_api/commands/__init__.py
nagra_panorama_api/commands/common.py
nagra_panorama_api/commands/dump_configs.py
nagra_panorama_api/commands/dump_dir.py
nagra_panorama_api/commands/software_update.py
nagra_panorama_api/commands/utils.py
nagra_panorama_api/constants.py
nagra_panorama_api/panorama.py
nagra_panorama_api/restapi/__init__.py
nagra_panorama_api/restapi/rest_resources.py
nagra_panorama_api/restapi/restapi.py
nagra_panorama_api/utils.py
nagra_panorama_api/xmlapi/__init__.py
nagra_panorama_api/xmlapi/base.py
nagra_panorama_api/xmlapi/client.py
nagra_panorama_api/xmlapi/constants.py
nagra_panorama_api/xmlapi/objects.py
nagra_panorama_api/xmlapi/types/__init__.py
nagra_panorama_api/xmlapi/types/config/__init__.py
nagra_panorama_api/xmlapi/types/config/address.py
nagra_panorama_api/xmlapi/types/config/devicegroup.py
nagra_panorama_api/xmlapi/types/config/interface.py
nagra_panorama_api/xmlapi/types/config/routing/__init__.py
nagra_panorama_api/xmlapi/types/config/routing/routing_table.py
nagra_panorama_api/xmlapi/types/config/rules/__init__.py
nagra_panorama_api/xmlapi/types/config/rules/nat.py
nagra_panorama_api/xmlapi/types/config/rules/rulebase.py
nagra_panorama_api/xmlapi/types/config/rules/security.py
nagra_panorama_api/xmlapi/types/config/zone.py
nagra_panorama_api/xmlapi/types/operations/__init__.py
nagra_panorama_api/xmlapi/types/operations/device.py
nagra_panorama_api/xmlapi/types/operations/job.py
nagra_panorama_api/xmlapi/types/operations/software.py
nagra_panorama_api/xmlapi/types/statistics.py
nagra_panorama_api/xmlapi/types/utils.py
nagra_panorama_api/xmlapi/utils.py
nagra_panorama_api-0.2.7.dist-info/LICENSE
nagra_panorama_api-0.2.7.dist-info/METADATA
nagra_panorama_api-0.2.7.dist-info/WHEEL
nagra_panorama_api-0.2.7.dist-info/entry_points.txt
nagra_panorama_api-0.2.7.dist-info/RECORD
