Metadata-Version: 2.1
Name: nagra-panorama-api
Version: 0.2.7
Summary: 
Author: David Gallay
Author-email: david.gallay@nagra.com
Requires-Python: >=3.7.0,<4.0.0
Classifier: Programming Language :: Python :: 3
Classifier: Programming Language :: Python :: 3.7
Classifier: Programming Language :: Python :: 3.8
Classifier: Programming Language :: Python :: 3.9
Classifier: Programming Language :: Python :: 3.10
Classifier: Programming Language :: Python :: 3.11
Classifier: Programming Language :: Python :: 3.12
Requires-Dist: click (>=8.1.7,<9.0.0)
Requires-Dist: diff-match-patch (>=20230430,<20230431)
Requires-Dist: lxml (>=4.9.3,<5.0.0)
Requires-Dist: pan-os-python (>=1.11.0,<2.0.0)
Requires-Dist: pyaml (>=23.5.8,<24.0.0)
Requires-Dist: pydantic (>=2.5.3,<3.0.0)
Requires-Dist: requests (>=2.31.0,<3.0.0)
Requires-Dist: rich (>=13.8.0,<14.0.0)
Requires-Dist: xmltodict (>=0.13.0,<0.14.0)
